azaka/__init__.py
azaka/client.py
azaka/exceptions.py
azaka/models.py
azaka/paginator.py
azaka/query.py
azaka/utils.py
azaka-0.4.2.dist-info/LICENSE
azaka-0.4.2.dist-info/METADATA
azaka-0.4.2.dist-info/WHEEL
azaka-0.4.2.dist-info/RECORD
